Workbook

Sheet Сводка
B2: Бюджет представительства «Детского Мира» в КНР
B3: Помесячные сметы на 6 месяцев (формулы от листа «Зарплаты и найм»)
B6: Блок | C6: CNY | D6: RUB
B7: CAPEX (единовременно, старт) | C7: =CAPEX!C12 | D7: =C7*'Зарплаты и найм'!$D20
B8: OPEX (6 мес., вкл. налог RO) | C8: ='OPEX помесячно'!I15 | D8: =C8*'Зарплаты и найм'!$D20
B9: ИТОГО за 6 месяцев | C9: =C7+C8 | D9: =C9*'Зарплаты и найм'!$D20

Sheet CAPEX
B2: CAPEX — единовременные затраты старта
B4: Статья | C4: CNY | D4: RUB | E4: Комментарий
B5: Юридическая регистрация RO | C5: ='Зарплаты и найм'!C35 | D5: =C5*'Зарплаты и найм'!$D20 | E5: 6–10 недель
B6: Регистрация ТМ в CNIPA (3 марки) | C6: ='Зарплаты и найм'!C36 | D6: =C6*'Зарплаты и найм'!$D20 | E6: до начала sourcing
B7: Офис: депозит + ремонт/мебель (~100 м²) | C7: ='Зарплаты и найм'!C37 | D7: =C7*'Зарплаты и найм'!$D20 | E7: Шанхай Grade A/B
B8: IT-капекс (ноутбуки, VPN, ERP-коннектор) | C8: ='Зарплаты и найм'!C38 | D8: =C8*'Зарплаты и найм'!$D20 | E8: подключение к HQ
B9: Стартовые командировки | C9: ='Зарплаты и найм'!C39 | D9: =C9*'Зарплаты и найм'!$D20 | E9: 3–4 поездки
B10: Оборудование ОТК | C10: ='Зарплаты и найм'!C40 | D10: =C10*'Зарплаты и найм'!$D20 | E10: полевой набор
B11: Резерв (contingency ~10%) | C11: ='Зарплаты и найм'!C41 | D11: =C11*'Зарплаты и найм'!$D20
B12: Итого CAPEX | C12: =SUM(C5:C11) | D12: =C12*'Зарплаты и найм'!$D20

Sheet Зарплаты и найм
B2: Исходные данные бюджета (редактировать серые ячейки)
B4: Роль | C4: Тип | D4: CNY/мес Зарплата+налоги | E4: Компенсации жилье + обучение детей | F4: Релокация единоразово | G4: M1 | H4: M2 | I4: M3 | J4: M4 | K4: M5 | L4: M6
B5: Директор (RU, экспат) | C5: Экспат | D5: 50000 | E5: 20000 | F5: 0 | G5: ● | H5: ● | I5: ● | J5: ● | K5: ● | L5: ●
B6: Технолог (RU, экспат) | C6: Экспат | D6: 30000 | E6: 20000 | F6: 20000 | L6: ●
B7: Кат. менеджер — игрушки (CN) | C7: Локальный | D7: 18500 | E7: 0 | F7: 0 | H7: ● | I7: ● | J7: ● | K7: ● | L7: ●
B8: Кат. менеджер — одежда (CN) | C8: Локальный | D8: 18500 | E8: 0 | F8: 0 | J8: ● | K8: ● | L8: ●
B9: Кат. менеджер — аксессуары (CN) | C9: Локальный | D9: 18500 | E9: 0 | F9: 0 | L9: ●
B10: Руководитель ОТК (CN) | C10: Локальный | D10: 18000 | E10: 0 | F10: 0 | H10: ● | I10: ● | J10: ● | K10: ● | L10: ●
B11: Бухгалтер штатный (CN) | C11: Локальный | D11: 16000 | E11: 0 | F11: 0 | I11: ● | J11: ● | K11: ● | L11: ●
B12: Инспектор ОТК №1 (CN) | C12: Локальный | D12: 10000 | E12: 0 | F12: 0 | J12: ● | K12: ● | L12: ●
B13: Инспектор ОТК №2 (CN) | C13: Локальный | D13: 10000 | E13: 0 | F13: 0 | L13: ●
B14: Офис-администратор (CN) | C14: Локальный | D14: 10000 | E14: 0 | F14: 0 | I14: ● | J14: ● | K14: ● | L14: ●
B15: Активных сотрудников | G15: =COUNTIF(G5:G14,"●") | H15: =COUNTIF(H5:H14,"●") | I15: =COUNTIF(I5:I14,"●") | J15: =COUNTIF(J5:J14,"●") | K15: =COUNTIF(K5:K14,"●") | L15: =COUNTIF(L5:L14,"●")
B17: Ставка соцвзносов (локальные) | D17: 0.35
B18: Ставка соцвзносов (экспаты) | D18: 0.15
B19: Налог RO (deemed) | D19: 0.1
B20: Курс CNY->RUB | D20: 12
B22: Прочие OPEX-драйверы
B23: Статья | C23: M1 | D23: M2 | E23: M3 | F23: M4 | G23: M5 | H23: M6
B24: Аутсорс-бухгалтерия | G24: 8000 | H24: 8000 | I24: 8000 | J24: 0 | K24: 0 | L24: 0
B25: Аренда офиса | G25: 6000 | H25: 6000 | I25: 20000 | J25: 20000 | K25: 20000 | L25: 20000
B26: Командировки и QC-выезды | G26: 5000 | H26: 10000 | I26: 20000 | J26: 30000 | K26: 35000 | L26: 35000
B27: IT / связь (opex) | G27: 3000 | H27: 5000 | I27: 5000 | J27: 5000 | K27: 5000 | L27: 5000
B28: Юр./комплаенс-ретейнер | G28: 10000 | H28: 8000 | I28: 5000 | J28: 5000 | K28: 5000 | L28: 5000
B29: Прочее (перевод, ресёрч, hospit.) | G29: 3000 | H29: 3000 | I29: 3000 | J29: 3000 | K29: 3000 | L29: 3000
B31: Распределение CAPEX по месяцам (для денежного потока) | G31: M1 | H31: M2 | I31: M3 | J31: M4 | K31: M5 | L31: M6
G32: 144000 | H32: 72000 | I32: 13000 | J32: 10000 | K32: 0 | L32: 0
B34: Статья | C34: CNY | D34: Комментарий
B35: Юридическая регистрация RO | C35: 20000 | D35: 6–10 недель
B36: Регистрация ТМ в CNIPA (3 марки) | C36: 10000 | D36: до начала sourcing
B37: Офис: депозит + ремонт/мебель (~100 м²) | C37: 15000 | D37: Шанхай Grade A/B
B38: IT-капекс (ноутбуки, VPN, ERP-коннектор) | C38: 50000 | D38: подключение к HQ
B39: Стартовые командировки | C39: 86000 | D39: 3–4 поездки
B40: Оборудование ОТК | C40: 10000 | D40: полевой набор
B41: Резерв (contingency ~10%) | C41: 48000

Sheet OPEX помесячно
B2: OPEX помесячно (CNY)
B4: Статья | C4: M1 | D4: M2 | E4: M3 | F4: M4 | G4: M5 | H4: M6 | I4: Итого
B5: ФОТ (gross) | C5: =SUMPRODUCT(--('Зарплаты и найм'!$G$5:$G$14="●"),'Зарплаты и найм'!$D$5:$D$14+'Зарплаты и найм'!$E$5:$E$14)+SUMPRODUCT(--('Зарплаты и найм'!$G$5:$G$14="●"),'Зарплаты и найм'!$F$5:$F$14) | D5: =SUMPRODUCT(--('Зарплаты и найм'!$H$5:$H$14="●"),'Зарплаты и найм'!$D$5:$D$14+'Зарплаты и найм'!$E$5:$E$14)+SUMPRODUCT(--('Зарплаты и найм'!$H$5:$H$14="●"),--('Зарплаты и найм'!$G$5:$G$14<>"●"),'Зарплаты и найм'!$F$5:$F$14) | E5: =SUMPRODUCT(--('Зарплаты и найм'!$I$5:$I$14="●"),'Зарплаты и найм'!$D$5:$D$14+'Зарплаты и найм'!$E$5:$E$14)+SUMPRODUCT(--('Зарплаты и найм'!$I$5:$I$14="●"),--('Зарплаты и найм'!$H$5:$H$14<>"●"),'Зарплаты и найм'!$F$5:$F$14) | F5: =SUMPRODUCT(--('Зарплаты и найм'!$J$5:$J$14="●"),'Зарплаты и найм'!$D$5:$D$14+'Зарплаты и найм'!$E$5:$E$14)+SUMPRODUCT(--('Зарплаты и найм'!$J$5:$J$14="●"),--('Зарплаты и найм'!$I$5:$I$14<>"●"),'Зарплаты и найм'!$F$5:$F$14) | G5: =SUMPRODUCT(--('Зарплаты и найм'!$K$5:$K$14="●"),'Зарплаты и найм'!$D$5:$D$14+'Зарплаты и найм'!$E$5:$E$14)+SUMPRODUCT(--('Зарплаты и найм'!$K$5:$K$14="●"),--('Зарплаты и найм'!$J$5:$J$14<>"●"),'Зарплаты и найм'!$F$5:$F$14) | H5: =SUMPRODUCT(--('Зарплаты и найм'!$L$5:$L$14="●"),'Зарплаты и найм'!$D$5:$D$14+'Зарплаты и найм'!$E$5:$E$14)+SUMPRODUCT(--('Зарплаты и найм'!$L$5:$L$14="●"),--('Зарплаты и найм'!$K$5:$K$14<>"●"),'Зарплаты и найм'!$F$5:$F$14) | I5: =SUM(C5:H5)
B6: Соцвзносы | C6: =ROUND(SUMPRODUCT(--('Зарплаты и найм'!$G$5:$G$14="●"),--('Зарплаты и найм'!$C$5:$C$14="Локальный"),'Зарплаты и найм'!$D$5:$D$14+'Зарплаты и найм'!$E$5:$E$14)*'Зарплаты и найм'!$D17+SUMPRODUCT(--('Зарплаты и найм'!$G$5:$G$14="●"),--('Зарплаты и найм'!$C$5:$C$14="Экспат"),'Зарплаты и найм'!$D$5:$D$14+'Зарплаты и найм'!$E$5:$E$14)*'Зарплаты и найм'!$D18,0) | D6: =ROUND(SUMPRODUCT(--('Зарплаты и найм'!$H$5:$H$14="●"),--('Зарплаты и найм'!$C$5:$C$14="Локальный"),'Зарплаты и найм'!$D$5:$D$14+'Зарплаты и найм'!$E$5:$E$14)*'Зарплаты и найм'!$D17+SUMPRODUCT(--('Зарплаты и найм'!$H$5:$H$14="●"),--('Зарплаты и найм'!$C$5:$C$14="Экспат"),'Зарплаты и найм'!$D$5:$D$14+'Зарплаты и найм'!$E$5:$E$14)*'Зарплаты и найм'!$D18,0) | E6: =ROUND(SUMPRODUCT(--('Зарплаты и найм'!$I$5:$I$14="●"),--('Зарплаты и найм'!$C$5:$C$14="Локальный"),'Зарплаты и найм'!$D$5:$D$14+'Зарплаты и найм'!$E$5:$E$14)*'Зарплаты и найм'!$D17+SUMPRODUCT(--('Зарплаты и найм'!$I$5:$I$14="●"),--('Зарплаты и найм'!$C$5:$C$14="Экспат"),'Зарплаты и найм'!$D$5:$D$14+'Зарплаты и найм'!$E$5:$E$14)*'Зарплаты и найм'!$D18,0) | F6: =ROUND(SUMPRODUCT(--('Зарплаты и найм'!$J$5:$J$14="●"),--('Зарплаты и найм'!$C$5:$C$14="Локальный"),'Зарплаты и найм'!$D$5:$D$14+'Зарплаты и найм'!$E$5:$E$14)*'Зарплаты и найм'!$D17+SUMPRODUCT(--('Зарплаты и найм'!$J$5:$J$14="●"),--('Зарплаты и найм'!$C$5:$C$14="Экспат"),'Зарплаты и найм'!$D$5:$D$14+'Зарплаты и найм'!$E$5:$E$14)*'Зарплаты и найм'!$D18,0) | G6: =ROUND(SUMPRODUCT(--('Зарплаты и найм'!$K$5:$K$14="●"),--('Зарплаты и найм'!$C$5:$C$14="Локальный"),'Зарплаты и найм'!$D$5:$D$14+'Зарплаты и найм'!$E$5:$E$14)*'Зарплаты и найм'!$D17+SUMPRODUCT(--('Зарплаты и найм'!$K$5:$K$14="●"),--('Зарплаты и найм'!$C$5:$C$14="Экспат"),'Зарплаты и найм'!$D$5:$D$14+'Зарплаты и найм'!$E$5:$E$14)*'Зарплаты и найм'!$D18,0) | H6: =ROUND(SUMPRODUCT(--('Зарплаты и найм'!$L$5:$L$14="●"),--('Зарплаты и найм'!$C$5:$C$14="Локальный"),'Зарплаты и найм'!$D$5:$D$14+'Зарплаты и найм'!$E$5:$E$14)*'Зарплаты и найм'!$D17+SUMPRODUCT(--('Зарплаты и найм'!$L$5:$L$14="●"),--('Зарплаты и найм'!$C$5:$C$14="Экспат"),'Зарплаты и найм'!$D$5:$D$14+'Зарплаты и найм'!$E$5:$E$14)*'Зарплаты и найм'!$D18,0) | I6: =SUM(C6:H6)
B7: Аутсорс-бухгалтерия | C7: ='Зарплаты и найм'!G24 | D7: ='Зарплаты и найм'!H24 | E7: ='Зарплаты и найм'!I24 | F7: ='Зарплаты и найм'!J24 | G7: ='Зарплаты и найм'!K24 | H7: ='Зарплаты и найм'!L24 | I7: =SUM(C7:H7)
B8: Аренда офиса | C8: ='Зарплаты и найм'!G25 | D8: ='Зарплаты и найм'!H25 | E8: ='Зарплаты и найм'!I25 | F8: ='Зарплаты и найм'!J25 | G8: ='Зарплаты и найм'!K25 | H8: ='Зарплаты и найм'!L25 | I8: =SUM(C8:H8)
B9: Командировки и QC-выезды | C9: ='Зарплаты и найм'!G26 | D9: ='Зарплаты и найм'!H26 | E9: ='Зарплаты и найм'!I26 | F9: ='Зарплаты и найм'!J26 | G9: ='Зарплаты и найм'!K26 | H9: ='Зарплаты и найм'!L26 | I9: =SUM(C9:H9)
B10: IT / связь (opex) | C10: ='Зарплаты и найм'!G27 | D10: ='Зарплаты и найм'!H27 | E10: ='Зарплаты и найм'!I27 | F10: ='Зарплаты и найм'!J27 | G10: ='Зарплаты и найм'!K27 | H10: ='Зарплаты и найм'!L27 | I10: =SUM(C10:H10)
B11: Юр./комплаенс-ретейнер | C11: ='Зарплаты и найм'!G28 | D11: ='Зарплаты и найм'!H28 | E11: ='Зарплаты и найм'!I28 | F11: ='Зарплаты и найм'!J28 | G11: ='Зарплаты и найм'!K28 | H11: ='Зарплаты и найм'!L28 | I11: =SUM(C11:H11)
B12: Прочее (перевод, ресёрч, hospit.) | C12: ='Зарплаты и найм'!G29 | D12: ='Зарплаты и найм'!H29 | E12: ='Зарплаты и найм'!I29 | F12: ='Зарплаты и найм'!J29 | G12: ='Зарплаты и найм'!K29 | H12: ='Зарплаты и найм'!L29 | I12: =SUM(C12:H12)
B13: Подытог (до налога RO) | C13: =SUM(C5:C12) | D13: =SUM(D5:D12) | E13: =SUM(E5:E12) | F13: =SUM(F5:F12) | G13: =SUM(G5:G12) | H13: =SUM(H5:H12) | I13: =SUM(C13:H13)
B14: Налог RO (deemed) | C14: =ROUND(C13*'Зарплаты и найм'!$D19,0) | D14: =ROUND(D13*'Зарплаты и найм'!$D19,0) | E14: =ROUND(E13*'Зарплаты и найм'!$D19,0) | F14: =ROUND(F13*'Зарплаты и найм'!$D19,0) | G14: =ROUND(G13*'Зарплаты и найм'!$D19,0) | H14: =ROUND(H13*'Зарплаты и найм'!$D19,0) | I14: =SUM(C14:H14)
B15: ИТОГО OPEX/мес | C15: =C13+C14 | D15: =D13+D14 | E15: =E13+E14 | F15: =F13+F14 | G15: =G13+G14 | H15: =H13+H14 | I15: =SUM(C15:H15)
B16: ИТОГО OPEX/мес, RUB | C16: =C15*'Зарплаты и найм'!$D20 | D16: =D15*'Зарплаты и найм'!$D20 | E16: =E15*'Зарплаты и найм'!$D20 | F16: =F15*'Зарплаты и найм'!$D20 | G16: =G15*'Зарплаты и найм'!$D20 | H16: =H15*'Зарплаты и найм'!$D20 | I16: =SUM(C16:H16)

Sheet Денежный поток
B2: Денежный поток (CAPEX + OPEX), CNY
B4: Статья | C4: M1 | D4: M2 | E4: M3 | F4: M4 | G4: M5 | H4: M6 | I4: Итого
B5: CAPEX | C5: ='Зарплаты и найм'!G32 | D5: ='Зарплаты и найм'!H32 | E5: ='Зарплаты и найм'!I32 | F5: ='Зарплаты и найм'!J32 | G5: ='Зарплаты и найм'!K32 | H5: ='Зарплаты и найм'!L32 | I5: =SUM(C5:H5)
B6: OPEX | C6: ='OPEX помесячно'!C15 | D6: ='OPEX помесячно'!D15 | E6: ='OPEX помесячно'!E15 | F6: ='OPEX помесячно'!F15 | G6: ='OPEX помесячно'!G15 | H6: ='OPEX помесячно'!H15 | I6: =SUM(C6:H6)
B7: Итого/мес | C7: =C5+C6 | D7: =D5+D6 | E7: =E5+E6 | F7: =F5+F6 | G7: =G5+G6 | H7: =H5+H6 | I7: =SUM(C7:H7)
B8: Итого/мес, RUB | C8: =C7*'Зарплаты и найм'!$D20 | D8: =D7*'Зарплаты и найм'!$D20 | E8: =E7*'Зарплаты и найм'!$D20 | F8: =F7*'Зарплаты и найм'!$D20 | G8: =G7*'Зарплаты и найм'!$D20 | H8: =H7*'Зарплаты и найм'!$D20 | I8: =SUM(C8:H8)
