Workbook

Sheet Сводка
B2: Бюджет представительства «Детского Мира» в КНР
B3: Помесячные сметы на первые 6 месяцев · Форма: RO (Шанхай + полевой ОТК Гуанчжоу)
B4: Валюты: CNY (основная), RUB справочно · Курс-ориентир: 1 CNY = 12 RUB
B6: Блок | C6: CNY | D6: RUB
B7: CAPEX (единовременно, старт) | C7: =CAPEX!C12 -> 239000 | D7: =C7*12 -> 2868000
B8: OPEX (6 мес., вкл. налог RO) | C8: ='OPEX помесячно'!I15 -> 1613920 | D8: =C8*12 -> 19367040
B9: ИТОГО за 6 месяцев | C9: =C7+C8 -> 1852920 | D9: =C9*12 -> 22235040
B11: Run-rate на 6-й месяц (полная команда): ~CNY 381 тыс./мес · годовой ~CNY 4,4–4,6 млн (~RUB 53–55 млн).
B12: Disclaimer: индикативные цифры на базе бенчмарков; требуют калибровки с HR/Finance.

Sheet CAPEX
B2: CAPEX — единовременные затраты старта
B4: Статья | C4: CNY | D4: RUB | E4: Комментарий
B5: Юридическая регистрация RO | C5: 20000 | D5: =C5*12 -> 240000 | E5: 6–10 недель
B6: Регистрация ТМ в CNIPA (3 марки) | C6: 10000 | D6: =C6*12 -> 120000 | E6: до начала sourcing
B7: Офис: депозит + ремонт/мебель (~100 м²) | C7: 15000 | D7: =C7*12 -> 180000 | E7: Шанхай Grade A/B
B8: IT-капекс (ноутбуки, VPN, ERP-коннектор) | C8: 50000 | D8: =C8*12 -> 600000 | E8: подключение к HQ
B9: Стартовые командировки | C9: 86000 | D9: =C9*12 -> 1032000 | E9: 3–4 поездки
B10: Оборудование ОТК | C10: 10000 | D10: =C10*12 -> 120000 | E10: полевой набор
B11: Резерв (contingency ~10%) | C11: 48000 | D11: =C11*12 -> 576000
B12: Итого CAPEX | C12: =SUM(C5:C11) -> 239000 | D12: =C12*12 -> 2868000 | E12: ≈ USD 74 тыс.

Sheet Зарплаты и найм
B2: Зарплатные ориентиры (gross, CNY/мес) и график найма
B4: Роль | C4: Тип | D4: CNY/мес Зарплата+налоги | E4: Компенсации жилье + обучение детей | F4: Релокация единоразово | G4: M1 | H4: M2 | I4: M3 | J4: M4 | K4: M5 | L4: M6
B5: Директор (RU, экспат) | C5: Экспат | D5: 50000 | E5: 20000 | G5: ● | H5: ● | I5: ● | J5: ● | K5: ● | L5: ●
B6: Технолог (RU, экспат) | C6: Экспат | D6: 30000 | E6: 20000 | F6: 20000 | L6: ●
B7: Кат. менеджер — игрушки (CN) | C7: Локальный | D7: 18500 | H7: ● | I7: ● | J7: ● | K7: ● | L7: ●
B8: Кат. менеджер — одежда (CN) | C8: Локальный | D8: 18500 | J8: ● | K8: ● | L8: ●
B9: Кат. менеджер — аксессуары (CN) | C9: Локальный | D9: 18500 | L9: ●
B10: Руководитель ОТК (CN) | C10: Локальный | D10: 18000 | H10: ● | I10: ● | J10: ● | K10: ● | L10: ●
B11: Бухгалтер штатный (CN) | C11: Локальный | D11: 16000 | I11: ● | J11: ● | K11: ● | L11: ●
B12: Инспектор ОТК №1 (CN) | C12: Локальный | D12: 10000 | J12: ● | K12: ● | L12: ●
B13: Инспектор ОТК №2 (CN) | C13: Локальный | D13: 10000 | L13: ●
B14: Офис-администратор (CN) | C14: Локальный | D14: 10000 | I14: ● | J14: ● | K14: ● | L14: ●
B15: Активных сотрудников | G15: 1 | H15: 3 | I15: 5 | J15: 6 | K15: 7 | L15: 10
B17: Соцвзносы: ~35% gross локального (CN) персонала; ~15% по экспатам (RU).

Sheet OPEX помесячно
B2: OPEX помесячно (CNY)
B4: Статья | C4: M1 | D4: M2 | E4: M3 | F4: M4 | G4: M5 | H4: M6 | I4: Итого
B5: ФОТ (gross) | C5: 60000 | D5: 88500 | E5: 143500 | F5: 169500 | G5: 221500 | H5: 221500 | I5: =SUM(C5:H5) -> 904500
B6: Соцвзносы | C6: 9000 | D6: 19000 | E6: 38200 | F6: 47300 | G6: 57100 | H6: 57100 | I6: =SUM(C6:H6) -> 227700
B7: Аутсорс-бухгалтерия | C7: 8000 | D7: 8000 | E7: 8000 | F7: 0 | G7: 0 | H7: 0 | I7: =SUM(C7:H7) -> 24000
B8: Аренда офиса | C8: 6000 | D8: 6000 | E8: 20000 | F8: 20000 | G8: 20000 | H8: 20000 | I8: =SUM(C8:H8) -> 92000
B9: Командировки и QC-выезды | C9: 5000 | D9: 10000 | E9: 20000 | F9: 30000 | G9: 35000 | H9: 35000 | I9: =SUM(C9:H9) -> 135000
B10: IT / связь (opex) | C10: 3000 | D10: 5000 | E10: 5000 | F10: 5000 | G10: 5000 | H10: 5000 | I10: =SUM(C10:H10) -> 28000
B11: Юр./комплаенс-ретейнер | C11: 10000 | D11: 8000 | E11: 5000 | F11: 5000 | G11: 5000 | H11: 5000 | I11: =SUM(C11:H11) -> 38000
B12: Прочее (перевод, ресёрч, hospit.) | C12: 3000 | D12: 3000 | E12: 3000 | F12: 3000 | G12: 3000 | H12: 3000 | I12: =SUM(C12:H12) -> 18000
B13: Подытог (до налога RO) | C13: =SUM(C5:C12) -> 104000 | D13: =SUM(D5:D12) -> 147500 | E13: =SUM(E5:E12) -> 242700 | F13: =SUM(F5:F12) -> 279800 | G13: =SUM(G5:G12) -> 346600 | H13: =SUM(H5:H12) -> 346600 | I13: =SUM(C13:H13) -> 1467200
B14: Налог RO (deemed ~10% расходов) | C14: =ROUND(C13*0.1,0) -> 10400 | D14: =ROUND(D13*0.1,0) -> 14750 | E14: =ROUND(E13*0.1,0) -> 24270 | F14: =ROUND(F13*0.1,0) -> 27980 | G14: =ROUND(G13*0.1,0) -> 34660 | H14: =ROUND(H13*0.1,0) -> 34660 | I14: =SUM(C14:H14) -> 146720
B15: ИТОГО OPEX/мес | C15: =C13+C14 -> 114400 | D15: =D13+D14 -> 162250 | E15: =E13+E14 -> 266970 | F15: =F13+F14 -> 307780 | G15: =G13+G14 -> 381260 | H15: =H13+H14 -> 381260 | I15: =SUM(C15:H15) -> 1613920
B16: ИТОГО OPEX/мес, RUB | C16: =C15*12 -> 1372800 | D16: =D15*12 -> 1947000 | E16: =E15*12 -> 3203640 | F16: =F15*12 -> 3693360 | G16: =G15*12 -> 4575120 | H16: =H15*12 -> 4575120 | I16: =SUM(C16:H16) -> 19367040

Sheet Денежный поток
B2: Денежный поток (CAPEX + OPEX), CNY
B4: Статья | C4: M1 | D4: M2 | E4: M3 | F4: M4 | G4: M5 | H4: M6 | I4: Итого
B5: CAPEX | C5: 320000 | D5: 161000 | E5: 30000 | F5: 20000 | G5: 0 | H5: 0 | I5: =SUM(C5:H5) -> 531000
B6: OPEX | C6: ='OPEX помесячно'!C15 -> 114400 | D6: ='OPEX помесячно'!D15 -> 162250 | E6: ='OPEX помесячно'!E15 -> 266970 | F6: ='OPEX помесячно'!F15 -> 307780 | G6: ='OPEX помесячно'!G15 -> 381260 | H6: ='OPEX помесячно'!H15 -> 381260 | I6: =SUM(C6:H6) -> 1613920
B7: Итого/мес | C7: =C5+C6 -> 434400 | D7: =D5+D6 -> 323250 | E7: =E5+E6 -> 296970 | F7: =F5+F6 -> 327780 | G7: =G5+G6 -> 381260 | H7: =H5+H6 -> 381260 | I7: =SUM(C7:H7) -> 2144920
B8: Итого/мес, RUB | C8: =C7*12 -> 5212800 | D8: =D7*12 -> 3879000 | E8: =E7*12 -> 3563640 | F8: =F7*12 -> 3933360 | G8: =G7*12 -> 4575120 | H8: =H7*12 -> 4575120 | I8: =SUM(C8:H8) -> 25739040
B10: CAPEX концентрируется в M1–M2 (регистрация, офис, IT, ТМ); далее — дооснащение ОТК и резерв.
